timelap/__init__.py
timelap/timelap.py
timelap-0.0.1.dist-info/METADATA
timelap-0.0.1.dist-info/WHEEL
timelap-0.0.1.dist-info/top_level.txt
timelap-0.0.1.dist-info/RECORD
