Metadata-Version: 2.2
Name: timelap
Version: 0.0.1
Summary: A simple time measuring library
Author: aftxrlifx
Requires-Python: >=3.7
Dynamic: author
Dynamic: description
Dynamic: description-content-type
Dynamic: requires-python
Dynamic: summary
